{
  "applications": "*",
  "changelogDate": "20230309173324",
  "dto": "no",
  "embedded": false,
  "entityTableName": "project_leadership",
  "fields": [
    {
      "fieldName": "createdat",
      "fieldType": "Instant"
    },
    {
      "fieldName": "updatedat",
      "fieldType": "Instant"
    }
  ],
  "fluentMethods": true,
  "jpaMetamodelFiltering": true,
  "name": "ProjectLeadership",
  "pagination": "pagination",
  "readOnly": false,
  "relationships": [
    {
      "otherEntityName": "projectRoles",
      "otherEntityRelationshipName": "projectleadershipProjectrole",
      "relationshipName": "projectrole",
      "relationshipType": "many-to-one"
    },
    {
      "otherEntityName": "projects",
      "otherEntityRelationshipName": "projectleadershipProject",
      "relationshipName": "project",
      "relationshipType": "many-to-one"
    },
    {
      "otherEntityName": "employees",
      "otherEntityRelationshipName": "projectleadershipEmployee",
      "relationshipName": "employee",
      "relationshipType": "many-to-one"
    }
  ],
  "service": "serviceClass"
}
