{
  "applications": "*",
  "changelogDate": "20230309173336",
  "dto": "no",
  "embedded": false,
  "entityTableName": "rating_categories",
  "fields": [
    {
      "fieldName": "name",
      "fieldType": "String",
      "fieldValidateRules": ["required", "maxlength"],
      "fieldValidateRulesMaxlength": "255"
    },
    {
      "fieldName": "effDate",
      "fieldType": "Instant",
      "fieldValidateRules": ["required"]
    },
    {
      "fieldName": "createdAt",
      "fieldType": "Instant",
      "fieldValidateRules": ["required"]
    },
    {
      "fieldName": "updatedAt",
      "fieldType": "Instant",
      "fieldValidateRules": ["required"]
    },
    {
      "fieldName": "endDate",
      "fieldType": "Instant"
    },
    {
      "fieldName": "version",
      "fieldType": "Integer",
      "fieldValidateRules": ["required"]
    }
  ],
  "fluentMethods": true,
  "jpaMetamodelFiltering": true,
  "name": "RatingCategories",
  "pagination": "pagination",
  "readOnly": false,
  "relationships": [
    {
      "otherEntityName": "pcRatingAttributesCategories",
      "otherEntityRelationshipName": "category",
      "relationshipName": "pcratingattributescategoriesCategory",
      "relationshipType": "one-to-many"
    }
  ],
  "service": "serviceClass"
}
